{
    "items" : [
      {
        "img": "https://nvb99.github.io/blog/src/img/slider01.jpg",
        "alt" : "Slider 01",
        "link" : "#"
      },
      {
        "img": "https://nvb99.github.io/blog/src/img/slider02.jpg",
        "alt" : "Slider 02",
        "link" : "#"
      },
      {
        "img": "https://nvb99.github.io/blog/src/img/slider02.jpg",
        "alt" : "Slider 02",
        "link" : "#"
      },
      {
        "img": "https://nvb99.github.io/blog/src/img/slider03.jpg",
        "alt" : "Slider 03",
        "link" : "#"
      },
      {
        "img": "https://nvb99.github.io/blog/src/img/slider04.jpg",
        "alt" : "Slider 04",
        "link" : "#"
      },
      {
        "img": "https://nvb99.github.io/blog/src/img/slider04.jpg",
        "alt" : "Slider 04",
        "link" : "#"
      },
      
    ]
  }
